DeriveAlive/DeriveAlive.py
DeriveAlive/__init__.py
DeriveAlive/optimize.py
DeriveAlive/rootfinding.py
DeriveAlive/spline.py
tests/__init__.py
tests/gradient_descent_demo.py
tests/test_DeriveAlive.py
tests/test_optimize.py
tests/test_rootfinding.py
tests/test_spline.py
DeriveAlive-0.0.7.dist-info/LICENSE
DeriveAlive-0.0.7.dist-info/METADATA
DeriveAlive-0.0.7.dist-info/WHEEL
DeriveAlive-0.0.7.dist-info/top_level.txt
DeriveAlive-0.0.7.dist-info/RECORD
